HaplyHAPI.py
__init__.py
HaplyHAPI-1.0.1.dist-info/METADATA
HaplyHAPI-1.0.1.dist-info/WHEEL
HaplyHAPI-1.0.1.dist-info/top_level.txt
HaplyHAPI-1.0.1.dist-info/RECORD
