Metadata-Version: 2.1
Name: HaplyHAPI
Version: 1.0.1
Summary: Python implementation of the haply hAPI
Author: Antoine Weill--Duflos (Haply Robotics)
Author-email: antoine@haply.co
Requires-Dist: pyserial
